seacucumber/backend.py
seacucumber/tasks.py
seacucumber/util.py
seacucumber/__init__.py
seacucumber/models.py
seacucumber/tests.py
seacucumber/management/__init__.py
seacucumber/management/commands/ses_usage.py
seacucumber/management/commands/__init__.py
seacucumber/management/commands/ses_address.py
seacucumber_py3-1.5.2.dist-info/RECORD
seacucumber_py3-1.5.2.dist-info/METADATA
seacucumber_py3-1.5.2.dist-info/WHEEL
seacucumber_py3-1.5.2.dist-info/DESCRIPTION.rst
seacucumber_py3-1.5.2.dist-info/metadata.json
seacucumber_py3-1.5.2.dist-info/top_level.txt
