Metadata-Version: 2.0
Name: seacucumber-py3
Version: 1.5.2
Summary: A Django email backend for Amazon Simple Email Service, backed by celery.
Home-page: https://github.com/gordon86/sea-cucumber
Author: Gordon Vu
Author-email: gordon.vu@gmail.com
License: MIT
Platform: any
Classifier: Environment :: Web Environment
Classifier: Development Status :: 5 - Production/Stable
Classifier: Intended Audience :: Developers
Classifier: License :: OSI Approved :: MIT License
Classifier: Operating System :: OS Independent
Classifier: Programming Language :: Python :: 3
Classifier: Topic :: Software Development :: Libraries :: Python Modules
Classifier: Framework :: Django
Requires-Dist: boto (>=2.25.0)
Requires-Dist: celery
